testrepo123/__init__.py
testrepo123/py.typed
testrepo123-0.0.0.dist-info/LICENSE
testrepo123-0.0.0.dist-info/METADATA
testrepo123-0.0.0.dist-info/WHEEL
testrepo123-0.0.0.dist-info/top_level.txt
testrepo123-0.0.0.dist-info/RECORD
