Metadata-Version: 2.1
Name: testrepo123
Version: 0.0.0
Summary: YOUR Tag HERE
Author: Armin Ariamajd
Maintainer: Armin Ariamajd
License: GNU AFFERO GENERAL PUBLIC LICENSE
Project-URL: Homepage, https://aariam.github.io/TestRepo123
Project-URL: Download, https://github.com/AAriam/TestRepo123/releases
Project-URL: News, https://aariam.github.io/TestRepo123/news
Project-URL: Documentation, https://aariam.github.io/TestRepo123
Project-URL: Issue-Tracker, https://github.com/AAriam/TestRepo123/issues
Project-URL: Sponsor, https://aariam.github.io/TestRepo123/contribute/collaborate/maintain/sponsor
Project-URL: Source, https://github.com/AAriam/TestRepo123
Keywords: FIRST KEYWORD,SECOND KEYWORD
Classifier: License :: OSI Approved :: GNU Affero General Public License v3 or later (AGPLv3+)
Classifier: Natural Language :: English
Classifier: Operating System :: MacOS
Classifier: Operating System :: Microsoft :: Windows
Classifier: Operating System :: POSIX :: Linux
Classifier: Programming Language :: Python :: 3 :: Only
Classifier: Programming Language :: Python :: 3.10
Classifier: Programming Language :: Python :: 3.11
Classifier: Programming Language :: Python :: 3.12
Classifier: Programming Language :: Python :: 3.9
Classifier: Typing :: Typed
Requires-Python: >=3.9
License-File: LICENSE
Requires-Dist: numpy >=1.21.2
